logic_processes_layer/__init__.py
logic_processes_layer/context.py
logic_processes_layer/results.py
logic_processes_layer/structures.py
logic_processes_layer/abc/__init__.py
logic_processes_layer/abc/abc_chain.py
logic_processes_layer/abc/abc_mapper.py
logic_processes_layer/abc/abc_pipeline.py
logic_processes_layer/extensions/__init__.py
logic_processes_layer/extensions/mappers.py
logic_processes_layer/extensions/process_as_subprocess.py
logic_processes_layer/extensions/conditions/__init__.py
logic_processes_layer/extensions/conditions/condition.py
logic_processes_layer/extensions/conditions/operator_enums.py
logic_processes_layer/extensions/conditions/skiped.py
logic_processes_layer/processors/__init__.py
logic_processes_layer/processors/base.py
logic_processes_layer/processors/decorators.py
logic_processes_layer/processors/meta.py
logic_processes_layer/protocols/__init__.py
logic_processes_layer/protocols/condition.py
logic_processes_layer/sub_processors/__init__.py
logic_processes_layer/sub_processors/base.py
logic_processes_layer/sub_processors/decorators.py
logic_processes_layer/sub_processors/meta.py
logic_processes_layer-1.2025.1.14.dist-info/LICENSE
logic_processes_layer-1.2025.1.14.dist-info/METADATA
logic_processes_layer-1.2025.1.14.dist-info/WHEEL
logic_processes_layer-1.2025.1.14.dist-info/top_level.txt
logic_processes_layer-1.2025.1.14.dist-info/RECORD
