Metadata-Version: 2.2
Name: logic_processes_layer
Version: 1.2025.1.14
Summary: Abstractions for create business logic
Author-email: "Sergei (Gefest) Romanchuk" <pod.cargoes.0u@icloud.com>
License: MIT License
Project-URL: homepage, https://github.com/GefMar/logic_layer
Classifier: License :: OSI Approved :: MIT License
Requires-Python: >=3.8
License-File: LICENSE
